aurelia/__init__.py
aurelia/aurelia_arpes.py
aurelia/aurelia_hdf5_saving.py
aurelia/aurelia_plots.py
aurelia/aurelia_static_vars.py
aurelia-0.1.0.dist-info/licenses/LICENSE
aurelia-0.1.0.dist-info/METADATA
aurelia-0.1.0.dist-info/WHEEL
aurelia-0.1.0.dist-info/top_level.txt
aurelia-0.1.0.dist-info/RECORD
