Metadata-Version: 2.4
Name: aurelia
Version: 0.1.0
Summary: Simulate realistic ARPES spectra with experimental artifacts for analysis and machine-learning applications.
Author: Matteo Michiardi
Author-email: MengXing Na <mengxing.na@gmail.com>
License: MIT
Project-URL: Homepage, https://github.com/qmlab-ubc-ca/aurelia
Project-URL: Documentation, https://github.com/qmlab-ubc-ca/aurelia/wiki
Requires-Python: >=3.8
License-File: LICENSE
Requires-Dist: numpy>=1.21
Requires-Dist: matplotlib>=3.5
Requires-Dist: scipy>=1.10
Requires-Dist: h5py>=3.8
Dynamic: license-file
